biblatex2bibtex/__init__.py
biblatex2bibtex/cli.py
biblatex2bibtex/data/biblatex2bibtex.conf
biblatex2bibtex-0.0.4.dist-info/LICENSE
biblatex2bibtex-0.0.4.dist-info/METADATA
biblatex2bibtex-0.0.4.dist-info/WHEEL
biblatex2bibtex-0.0.4.dist-info/entry_points.txt
biblatex2bibtex-0.0.4.dist-info/top_level.txt
biblatex2bibtex-0.0.4.dist-info/RECORD
