Metadata-Version: 2.1
Name: biblatex2bibtex
Version: 0.0.4
Summary: Convert biblatex files to bibtex.
Home-page: https://github.com/fmatter/biblatex2bibtex
Author: Florian Matter
Author-email: florianmatter@gmail.com
Project-URL: Bug Tracker, https://github.com/fmatter/biblatex2bibtex/issues
Keywords: biblatex,bibtex
Classifier: Development Status :: 2 - Pre-Alpha
Classifier: Intended Audience :: Science/Research
Classifier: License :: OSI Approved :: Apache Software License
Classifier: Natural Language :: English
Classifier: Programming Language :: Python :: 3
Classifier: Programming Language :: Python :: 3.7
Classifier: Programming Language :: Python :: 3.8
Classifier: Programming Language :: Python :: 3.9
Classifier: Programming Language :: Python :: 3.10
License-File: LICENSE
Requires-Dist: colorlog
Requires-Dist: argparse
Requires-Dist: bibtexparser (>=1.4.0)
Requires-Dist: pybtex (>=0.24.0)
Provides-Extra: dev
Requires-Dist: bump2version ; extra == 'dev'
Requires-Dist: coverage[toml] ; extra == 'dev'
Requires-Dist: prospector (==1.10.2) ; extra == 'dev'
Requires-Dist: isort ; extra == 'dev'
Requires-Dist: pytest ; extra == 'dev'
Requires-Dist: pytest-cov ; extra == 'dev'
Requires-Dist: sphinx ; extra == 'dev'
Requires-Dist: sphinx-rtd-theme ; extra == 'dev'
Requires-Dist: sphinx-autoapi ; extra == 'dev'
Requires-Dist: sphinxcontrib-napoleon ; extra == 'dev'
Requires-Dist: tox ; extra == 'dev'
Requires-Dist: myst-parser ; extra == 'dev'
Requires-Dist: flake8 ; extra == 'dev'
Requires-Dist: twine ; extra == 'dev'
Requires-Dist: jinja2 ; extra == 'dev'
Requires-Dist: keepachangelog ; extra == 'dev'
Provides-Extra: publishing
Requires-Dist: twine ; extra == 'publishing'
Requires-Dist: wheel ; extra == 'publishing'
